winamp_driver.py
karaokemanagerwinampdriver-1.0.3.dist-info/METADATA
karaokemanagerwinampdriver-1.0.3.dist-info/WHEEL
karaokemanagerwinampdriver-1.0.3.dist-info/top_level.txt
karaokemanagerwinampdriver-1.0.3.dist-info/RECORD
