Metadata-Version: 2.1
Name: karaokemanagerwinampdriver
Version: 1.0.3
Summary: Winamp driver for KaraokeManager
Home-page: https://github.com/peeveen/karaokemanagerwinampdriver
Author: Steven Frew
Author-email: steven.fullhouse@gmail.com
License: MIT
Download-URL: https://pypi.org/project/karaokemanagerwinampdriver/
Keywords: Winamp,KaraokeManager
Platform: UNKNOWN
Requires-Dist: pywin32
